matplotlib_surface_plotting/__init__.py
matplotlib_surface_plotting/colors.py
matplotlib_surface_plotting/geometry.py
matplotlib_surface_plotting/matplotlib_surface_plotting.py
matplotlib_surface_plotting/transformations.py
matplotlib_surface_plotting-0.14.dist-info/licenses/LICENSE
matplotlib_surface_plotting-0.14.dist-info/METADATA
matplotlib_surface_plotting-0.14.dist-info/WHEEL
matplotlib_surface_plotting-0.14.dist-info/top_level.txt
matplotlib_surface_plotting-0.14.dist-info/RECORD
