Metadata-Version: 2.4
Name: matplotlib_surface_plotting
Version: 0.14
Summary: Brain mesh plotting in matplotlib
Home-page: https://github.com/kwagstyl/matplotlib_surface_plotting
License-File: LICENSE
Requires-Dist: nibabel
Requires-Dist: matplotlib>=3.3.2
Provides-Extra: test
Requires-Dist: pytest; extra == "test"
Requires-Dist: pytest-cov; extra == "test"
Dynamic: description
Dynamic: description-content-type
Dynamic: home-page
Dynamic: license-file
Dynamic: provides-extra
Dynamic: requires-dist
Dynamic: summary
